{
  "type": "FeatureCollection",
  "features": [
    {
      "type": "Feature",
      "geometry": {
        "type": "Point",
        "coordinates": [-122.2687081,37.808217]
      },
      "properties": {
        "marker-symbol": "bakery",
        "name": "Donut Savant",
        "address": "1934 Broadway",
		"phone": "(206) 409-3770"
      }
    }
  ]
}